Azog/__init__.py
Azog/utils.py
Azog/base/__init__.py
Azog/base/base_host.py
Azog/base/command.py
Azog/base/exception.py
Azog/host/__init__.py
Azog/host/host.py
Azog/server_info/__init__.py
Azog/server_info/cpu_info.py
Azog/server_info/disk_info.py
Azog/server_info/info_utils.py
Azog/server_info/ram_info.py
Azog/server_info/system_info.py
Azog-0.2.dist-info/METADATA
Azog-0.2.dist-info/WHEEL
Azog-0.2.dist-info/top_level.txt
Azog-0.2.dist-info/RECORD
