Metadata-Version: 2.1
Name: Azog
Version: 0.2
Author: bitex47
Author-email: xyjy5247@gmail.com
Requires-Python: >=3.6
Requires-Dist: paramiko (>=2.10.1)
